[
  {
    "ContainingType": "ArtonitRESTAPI.APIControllers.AuthController",
    "Method": "Login",
    "RelativePath": "login",
    "HttpMethod": "GET",
    "IsController": true,
    "Order": 0,
    "Parameters": [
      {
        "Name": "username",
        "Type": "System.String",
        "IsRequired": false
      },
      {
        "Name": "pasword",
        "Type": "System.String",
        "IsRequired": false
      }
    ],
    "ReturnTypes": []
  },
  {
    "ContainingType": "OpenAPIArtonit.APIControllers.PersonController",
    "Method": "Get",
    "RelativePath": "Person",
    "HttpMethod": "GET",
    "IsController": true,
    "Order": 0,
    "Parameters": [
      {
        "Name": "id",
        "Type": "System.Int32",
        "IsRequired": false
      }
    ],
    "ReturnTypes": []
  },
  {
    "ContainingType": "OpenAPIArtonit.APIControllers.PersonController",
    "Method": "Add",
    "RelativePath": "Person",
    "HttpMethod": "POST",
    "IsController": true,
    "Order": 0,
    "Parameters": [
      {
        "Name": "body",
        "Type": "OpenAPIArtonit.Model.PersonPostSee",
        "IsRequired": true
      }
    ],
    "ReturnTypes": []
  },
  {
    "ContainingType": "OpenAPIArtonit.APIControllers.PersonController",
    "Method": "Update",
    "RelativePath": "Person",
    "HttpMethod": "PATCH",
    "IsController": true,
    "Order": 0,
    "Parameters": [
      {
        "Name": "body",
        "Type": "OpenAPIArtonit.Model.PersonPach",
        "IsRequired": true
      }
    ],
    "ReturnTypes": []
  },
  {
    "ContainingType": "OpenAPIArtonit.APIControllers.PersonController",
    "Method": "Delite",
    "RelativePath": "Person",
    "HttpMethod": "DELETE",
    "IsController": true,
    "Order": 0,
    "Parameters": [
      {
        "Name": "id",
        "Type": "System.Int32",
        "IsRequired": false
      }
    ],
    "ReturnTypes": []
  },
  {
    "ContainingType": "OpenAPIArtonit.APIControllers.PersonController",
    "Method": "GetList",
    "RelativePath": "Person/GetList",
    "HttpMethod": "GET",
    "IsController": true,
    "Order": 0,
    "Parameters": [
      {
        "Name": "pageIndex",
        "Type": "System.Int32",
        "IsRequired": false
      },
      {
        "Name": "pageSize",
        "Type": "System.Int32",
        "IsRequired": false
      }
    ],
    "ReturnTypes": []
  }
]